REGEASE/__init__.py
REGEASE/regease.py
regease-1.0.0.dist-info/LICENSE
regease-1.0.0.dist-info/METADATA
regease-1.0.0.dist-info/WHEEL
regease-1.0.0.dist-info/top_level.txt
regease-1.0.0.dist-info/RECORD
