Metadata-Version: 2.1
Name: regease
Version: 1.0.0
Summary: Simplify the Regular Expression
Home-page: UNKNOWN
Author: Jaskamal Singla
Author-email: <jaskamal252007@gmail.com>
License: UNKNOWN
Keywords: python,regex,regular expressions,validation,password,username,email
Platform: UNKNOWN
Classifier: Programming Language :: Python :: 3
Classifier: Programming Language :: Python :: 2
Classifier: Operating System :: Unix
Classifier: Operating System :: MacOS :: MacOS X
Classifier: Operating System :: Microsoft :: Windows
